{"scr":"ApplyLoan","layout":"All","id":"D0","displayname":"D0","screenType":"MAIN","ifaces":["aclo01__Liabilities","aclo01__UploadDocs"],"containers":{"name":["aclo01__ApplyLoan__ct_tbl_1","aclo01__ApplyLoan__ct_tbl_2","aclo01__ApplyLoan__ct_frm_4","aclo01__ApplyLoan__ct_frm_5","aclo01__ApplyLoan__ct_frm_6","aclo01__ApplyLoan__ct_nav_2","aclo01__ApplyLoan__ct_frm_7"],"type":["TABLE","TABLE","FORM","FORM","FORM","NAVBAR","FORM"],"custom":["N","N","N","N","N","N","N"],"multiRec":["Y","Y","N","N","N","N","N"],"ro":["N","N","Y","N","N","N","N"],"pgStyle":["","","","","","",""],"pgSize":[999,999,999,999,999,999,999],"childs":["","","","","","",""],"noOfIfaces":[1,1,0,0,0,0,0],"ifaces":["aclo01__Liabilities","aclo01__UploadDocs"],"noOfNodes":[1,1,0,0,0,0,0],"nodes":["aclo01__Liabilities__o__liability","aclo01__UploadDocs__o__Docs"],"noOfElms":[4,3,1,1,5,1,1],"ui":["N","N","Y","Y","Y","Y","Y"],"elms":["aclo01__Liabilities__o__liability__Bank","aclo01__Liabilities__o__liability__FinancingType","aclo01__Liabilities__o__liability__Amoount","aclo01__Liabilities__o__liability__MonthlyInstallment","aclo01__UploadDocs__o__Docs__DocType","aclo01__ApplyLoan__el_fil_1","aclo01__UploadDocs__o__Docs__DocImg","aclo01__ApplyLoan__el_txt_3","aclo01__ApplyLoan__el_btn_2","aclo01__ApplyLoan__el_dpd_3","aclo01__ApplyLoan__el_inp_3","aclo01__ApplyLoan__el_inp_4","aclo01__ApplyLoan__el_inp_7","aclo01__ApplyLoan__el_inp_6","aclo01__ApplyLoan__el_btn_3","aclo01__ApplyLoan__viewimg"],"eUi":["N","N","N","N","N","Y","N","Y","Y","Y","Y","Y","Y","Y","Y","Y"],"eCustom":["N","N","N","N","N","N","N","N","N","N","N","N","N","N","N","N"],"elmType":["INPUTBOX","DROPDOWN","INPUTBOX","INPUTBOX","DROPDOWN","FILEBROWSER","IMAGE","TEXT","BUTTON","DROPDOWN","INPUTBOX","INPUTBOX","INPUTBOX","TEXTAREA","BUTTON","IMAGE"],"eRo":["N","N","N","N","N","N","N","N","N","N","N","N","N","N","N","N"],"eMask":["","","","","","","","","","","","","","","",""],"eRtFmt":["N","N","N","N","","","","","","","N","N","N","N","",""],"eSkipFmt":["N","N","N","N","","","","N","","","N","N","N","N","",""],"eLiteral":["N","N","N","N","","","","N","","","N","N","N","N","",""],"eLovId":["aclo01__","aclo01__","aclo01__","aclo01__","aclo01__","aclo01__","aclo01__","aclo01__","aclo01__","aclo01__","aclo01__","aclo01__","aclo01__","aclo01__","aclo01__","aclo01__"],"eLovWidth":["lcol","lcol","lcol","lcol","lcol","lcol","lcol","lcol","lcol","lcol","lcol","lcol","lcol","lcol","lcol","lcol"],"eLovMinWidth":["","","","","","","","","","","","","","","",""],"noOfeLovRf":[0,0,0,0,0,0,0,0,0,0,0,0,0,0,0,0],"noOfeLovBv":[0,0,0,0,0,0,0,0,0,0,0,0,0,0,0,0]},"groups":{"name":["GRP_ApplyLoan_1","GRP_ApplyLoan_2"],"noOfNodes":[1,1],"nodes":["aclo01__Liabilities__o__liability","aclo01__UploadDocs__o__Docs"],"noOfContainers":[1,1],"containers":["aclo01__ApplyLoan__ct_tbl_1","aclo01__ApplyLoan__ct_tbl_2"]},"uiInits":{"dropDown":[["aclo01__Liabilities__o__liability__FinancingType_0","","ANDROID-HOLO","CENTER","N","N","SIMPLE","N"],["aclo01__UploadDocs__o__Docs__DocType_0","","","","","","SIMPLE","N"],["aclo01__ApplyLoan__el_dpd_3","","","","","","SIMPLE","N"]]},"scripts":["ApplyLoan.js"],"scrProps":["","","","","","","","","pri"]}