{"name":"acpr01__CorporateDirectorsInsert","type":"DATABASE","dateTimeFormat":"yyyy-MM-dd HH:mm:ss","offline":"N","session":"N","correctReq":"N","noOfReqNodes":2,"correctRes":"N","noOfResNodes":1,"noOFaultNodes":1,"nodes":["acpr01__CorporateDirectorsInsert_Req","tbDbmiCorporateDirectors","acpr01__CorporateDirectorsInsert_Res","acpr01__CorporateDirectorsInsert_Flt"],"noOfNodeElms":[0,9,0,0],"nExtName":["acpr01__CorporateDirectorsInsert_Req","tbDbmiCorporateDirectors","acpr01__CorporateDirectorsInsert_Res","acpr01__CorporateDirectorsInsert_Flt"],"nMultiRec":["N","Y","N","N"],"nParent":["","acpr01__CorporateDirectorsInsert_Req","",""],"nParents":["","acpr01__CorporateDirectorsInsert_Req","",""],"nChilds":["tbDbmiCorporateDirectors","","",""],"nRelType":["1:1","1:N","1:1","1:1"],"nMrParent":["acpr01__CorporateDirectorsInsert_Req","tbDbmiCorporateDirectors","acpr01__CorporateDirectorsInsert_Res","acpr01__CorporateDirectorsInsert_Flt"],"elms":["corporateId","directorSequence","designation","name","mobile","email","landline","socialMediaProfile","directorPhoto"],"eExtName":["corporateId","directorSequence","designation","name","mobile","email","landline","socialMediaProfile","directorPhoto"],"eDataType":["STRING","INTEGER","STRING","STRING","STRING","STRING","STRING","STRING","STRING"],"eMinVal":["","","","","","","","",""],"eMaxVal":["","","","","","","","",""],"eMaxDec":["","","","","","","","",""],"eLenType":["F","F","F","F","F","F","F","F","F"],"eMinLen":["","","","","","","","",""],"eMaxLen":["","","","","","","","",""],"eArr":["N","N","N","N","N","N","N","N","N"],"ePattern":["","","","","","","","",""],"eMand":["N","N","N","N","N","N","N","N","N"],"eRelNode":["","","","","","","","",""],"eRelElm":["","","","","","","","",""]}