{"name":"intb01__FTService","type":"CUSTOM","offline":"N","session":"N","correctReq":"Y","noOfReqNodes":2,"correctRes":"N","noOfResNodes":1,"noOFaultNodes":1,"nodes":["intb01__FTService_Req","fundsTransferDetails","intb01__FTService_Res","intb01__FTService_Flt"],"noOfNodeElms":[0,9,0,0],"nExtName":["intb01__FTService_Req","fundsTransferDetails","intb01__FTService_Res","intb01__FTService_Flt"],"nMultiRec":["N","N","N","N"],"nParent":["","intb01__FTService_Req","",""],"nParents":["","intb01__FTService_Req","",""],"nChilds":["fundsTransferDetails","","",""],"nRelType":["1:1","1:1","1:1","1:1"],"nMrParent":["intb01__FTService_Req","fundsTransferDetails","intb01__FTService_Res","intb01__FTService_Flt"],"elms":["txnId","fromAccount","toAccount","transferType","txnDesc","amount","currency","txnDate","beneficiaryId"],"eExtName":["txnId","fromAccount","toAccount","transferType","desc","amount","currency","txnDate","beneficiaryId"],"eDataType":["STRING","STRING","STRING","STRING","STRING","NUMBER","STRING","DATETIME","STRING"],"eMinVal":["","","","","","","","",""],"eMaxVal":["","","","","","","","",""],"eMaxDec":["","","","","","","","",""],"eLenType":["F","F","F","F","F","F","F","F","F"],"eMinLen":["","","","","","","","",""],"eMaxLen":["","","","","","","","",""],"eArr":["N","N","N","N","N","N","N","N","N"],"ePattern":["","","","","","","","",""],"eMand":["N","N","N","N","N","N","N","N","N"],"eRelNode":["","","","","","","","",""],"eRelElm":["","","","","","","","",""]}