{"lits":{"en":{"LIT_TOACCOUNT":"To Account","LIT_TXNFREQUENCY":"Txn Frequency","LIT_FROMACCOUNT":"From Account","LIT_TBDBTPSIFUNDSTRANSFER":"Tb Dbtp Si Funds Transfer","LIT_OTHERBANK_INT":"Other Bank(INT)","LIT_USERID":"User Id","LIT_CONFIRM":"Confirm","LIT_TBDBMICORPSTANDINGINSTRUCTIONS":"Tb Dbmi Corp Standing Instructions","LIT_FROMACC":"From Account","LIT_VERIFY":"Verify","LIT_CORPORATEID":"Corporate Id","LIT_WITHINBANK":"Within the Bank","LIT_NEXTSTAGE":"Next Stage","LIT_STANDING_INSTRUCTION":"Standing Instructions","LIT_DETAILS":"Details","LIT_STARTDATE":"Start Date","LIT_CONTINUE":"Continue","LIT_BENEFADRESS":"Beneficiary Address","LIT_APPZILLONFAULT":"Appzillon Fault","LIT_BENEFICIARYNAME":"Beneficiary Name","LIT_FREQUENCY":"Frequency","LIT_BULKUPLOAD":"Bulk Upload","LIT_FUNCTIONID":"Function Id","LIT_CHARGEWHOM":"Charge Whom","LIT_REMARKS":"Remarks","LIT_OTHERBANK_DOM":"Other Bank(DOM)","LIT_APPZILLONREQUEST":"Appzillon Request","LIT_TBDBMIWORKFLOWRULEDETAIL":"Tb Dbmi Workflow Rule Detail","LIT_STAGEID":"Stage Id","LIT_RULEEQUATION":"Rule Equation","LIT_CURRENCY":"Currency","LIT_STATUS":"Status","LIT_ENDDATE":"End Date","LIT_TRANSFERTYPE":"Transfer Type","LIT_PAYEENAME":"Payee Account","LIT_REFERENCENO":"Reference No","LIT_TOACC":"To Account","LIT_AMOUNT":"Amount","LIT_NEXTEXECUTIONDATE":"Next Execution Date","LIT_TRANSACTIONDATE":"Transaction Date","LIT_MULTITRANSFERS":"Multi Transfers","LIT_TRANSFERSHIS":"Transfers History","LIT_EDIT":"Edit","LIT_BENFBANKNAME":"Beneficiary Bank Name","LIT_TXNDESC":"Txn Desc","LIT_TXNID":"Txn Id","LIT_GO":"Go","LIT_APPLY":"Apply","LIT_OWNAC":"Own Account","LIT_SWIFTCODE":"Swift Code","LIT_APPZILLONRESPONSE":"Appzillon Response","LIT_CANCEL":"Cancel","LIT_RULESEQUENCE":"Rule Sequence","LIT_NOOFTIMES":"No Of Times","LIT_OK":"Ok","LIT_NICKNAME":"Nick Name","LIT_AMOUNTCURRENCY":"Amount Currency","LIT_MANAGERBENF":"Manage Beneficiary"}},"msgs":{"en":{"ACFT_DETAILSSUCC":"SOwn Account Details have been submitted successfully","APZ-SVR-FAV":"SFavourite Added Successfully","APZ-FT-REJCT":"IFunds Transfer details have been rejected successfully","ACFT_AMOUNT":"IPlease enter the valid amount","APZ-TSK-SUCS":"ITask has been completed","SEARCH_CHK":"Iplease select search type","APZ_ACFT01_MANDATORY":"EPlease provide value for mandatory field(s)"}},"lovs":{},"workflows":[{"workflowid":"SICS","workflowdetails":[{"stageid":"SICS","screenid":"SIClosure","seqno":"1"},{"stageid":"SICS","screenid":"SIClosureApprove","seqno":"2"},{"stageid":"SICS","screenid":null,"seqno":"3"}]},{"workflowid":"SIDOM","workflowdetails":[{"stageid":"DETAILS","screenid":"OtherBankDOM","seqno":"1"},{"stageid":"VERIFY","screenid":"OtherBankDOMVerify","seqno":"2"},{"stageid":"APPROVE","screenid":"OtherBankDOMApprove","seqno":"3"},{"stageid":"CONFIRM","screenid":"OtherBankDOMConfirm","seqno":"4"}]},{"workflowid":"SIOA","workflowdetails":[{"stageid":"DETAILS","screenid":"OwnAccount","seqno":"1"},{"stageid":"VERIFY","screenid":"OwnAccountVerify","seqno":"2"},{"stageid":"APPROVE","screenid":"OwnAccountApprove","seqno":"3"},{"stageid":"CONFIRM","screenid":"OwnAccountConfirmation","seqno":"4"}]},{"workflowid":"SIWB","workflowdetails":[{"stageid":"DETAILS","screenid":"WithinBank","seqno":"1"},{"stageid":"VERIFY","screenid":"WithinBankVerify","seqno":"2"},{"stageid":"APPROVE","screenid":"WithinBankApprove","seqno":"3"},{"stageid":"CONFIRM","screenid":"WithinBankConfirmation","seqno":"4"}]}],"microApps":["roleAc","acclt","acre01","acbs01","acwf01","bein01","benf01","accdtl","tscm01","siint1"],"deviceGroups":[{"name":"All","os":"ALL","width":"1000","height":"2000","orientation":"ANY"},{"name":"Mobile","os":"ALL","width":"342","height":"586","orientation":"ANY"}],"conversations":{"convids":[],"convdescs":[],"rulesbeans":[],"nlpsbeans":[],"convinterfaces":{},"convscripts":{}},"screens":["ModifySI","NewSI","OtherBankDOM","OtherBankDOMApprove","OtherBankDOMVerify","OwnAccount","OwnAccountApprove","OwnAccountVerify","SIClosure","SIClosureApprove","SIDetails","StandingInstructions","WithinBank","WithinBankApprove","WithinBankVerify"],"loMap":{"ModifySI":{"All":{"PORTRAIT":"All","LANDSCAPE":"All"}},"NewSI":{"All":{"PORTRAIT":"All","LANDSCAPE":"All"}},"OtherBankDOM":{"All":{"PORTRAIT":"All","LANDSCAPE":"All"}},"OtherBankDOMApprove":{"All":{"PORTRAIT":"All","LANDSCAPE":"All"}},"OtherBankDOMVerify":{"All":{"PORTRAIT":"All","LANDSCAPE":"All"}},"OwnAccount":{"All":{"PORTRAIT":"All","LANDSCAPE":"All"}},"OwnAccountApprove":{"All":{"PORTRAIT":"All","LANDSCAPE":"All"}},"OwnAccountVerify":{"All":{"PORTRAIT":"All","LANDSCAPE":"All"}},"SIClosure":{"All":{"PORTRAIT":"All","LANDSCAPE":"All"}},"SIClosureApprove":{"All":{"PORTRAIT":"All","LANDSCAPE":"All"}},"SIDetails":{"All":{"PORTRAIT":"All","LANDSCAPE":"All"}},"StandingInstructions":{"All":{"PORTRAIT":"All","LANDSCAPE":"All"},"Mobile":{"PORTRAIT":"Mobile","LANDSCAPE":"Mobile"}},"WithinBank":{"All":{"PORTRAIT":"All","LANDSCAPE":"All"}},"WithinBankApprove":{"All":{"PORTRAIT":"All","LANDSCAPE":"All"}},"WithinBankVerify":{"All":{"PORTRAIT":"All","LANDSCAPE":"All"}}},"userPrefs":{},"props":{"offlineSupport":"N","appId":"acsi01","firstPage":"StandingInstructions","serverToken":"rn6xMCdoNHWMec+6Dk/9FfC36KmK5wiONpyNTE7hKME=","defaultAuthorization":"N","otpReqd":"N","trackLocation":"N","serverUrl":"http://localhost:8080/AppzillonCorpServer/Appzillon","auditLogReqd":"N","noOfLogLines":100,"logLevel":"D","authenticationType":"#DeviceId","sendLog":"N","useProcessJson":"N","enableMockServer":true,"enableAnimation":"Y","sslPinning":"N","trustAllCertificates":"N","payloadEncryption":"N","dataIntegrity":"Y","enableServer":"Y"},"internalInterfaces":{},"appzillonVersion":"3.5.21"}