{"offlineSupport":"N","appId":"ACLI01","firstPage":"LoginBCSS","serverToken":"P7dKflXNoljK1u9cTaI7ow==","defaultAuthorization":"N","otpReqd":"N","trackLocation":"N","serverUrl":"http://localhost:8080/AppzillonCorpServer/Appzillon","auditLogReqd":"N","noOfLogLines":100,"logLevel":"D","authenticationType":"#DeviceId","sendLog":"N","useProcessJson":"N","enableMockServer":true,"enableAnimation":"Y","sslPinning":"N","trustAllCertificates":"N","payloadEncryption":"N","dataIntegrity":"Y","enableServer":"Y"}