{"name":"authma__AccountGroup","type":"CUSTOM","offline":"N","session":"Y","correctReq":"N","noOfReqNodes":1,"correctRes":"Y","noOfResNodes":2,"noOFaultNodes":1,"nodes":["authma__AccountGroup_Req","authma__AccountGroup_Res","details","authma__AccountGroup_Flt"],"noOfNodeElms":[0,3,3,0],"nExtName":["authma__AccountGroup_Req","authma__AccountGroup_Res","details","authma__AccountGroup_Flt"],"nMultiRec":["N","Y","Y","N"],"nParent":["","","authma__AccountGroup_Res",""],"nParents":["","","authma__AccountGroup_Res",""],"nChilds":["","details","",""],"nRelType":["1:1","1:N","1:N","1:1"],"nMrParent":["authma__AccountGroup_Req","authma__AccountGroup_Res","details","authma__AccountGroup_Flt"],"elms":["name","description","active","acc_type","acc_no","access_rights"],"eExtName":["NewElement","NewElement","NewElement","NewElement","NewElement","NewElement"],"eDataType":["STRING","STRING","STRING","STRING","STRING","STRING"],"eMinVal":["","","","","",""],"eMaxVal":["","","","","",""],"eMaxDec":["","","","","",""],"eLenType":["F","F","F","F","F","F"],"eMinLen":["","","","","",""],"eMaxLen":["","","","","",""],"eArr":["N","N","N","N","N","N"],"ePattern":["","","","","",""],"eMand":["N","N","N","N","N","N"],"eRelNode":["","","","","",""],"eRelElm":["","","","","",""]}