{"lits":{"en":{"LIT_DATEOFCREATION":"Date Of Creation","LIT_PROMOTIONID":"Promotion Id","LIT_APPZILLONFAULT":"Appzillon Fault","LIT_CREATEDBY":"Created By","LIT_GO":"Go","LIT_USERID":"User Id","LIT_IMG":"Img","LIT_MSG":"Msg","LIT_APPZILLONRESPONSE":"Appzillon Response","LIT_CANCEL":"Cancel","LIT_OK":"Ok","LIT_APPZILLONREQUEST":"Appzillon Request","LIT_TBDBMIPROMOTIONS":"Tb Dbmi Promotions","LIT_TYPE":"Type","LIT_CATEGORY":"Category","LIT_HEADER":"Header","LIT_STATUS":"Status","LIT_ID":"Id"}},"msgs":{},"lovs":{},"deviceGroups":[{"name":"Web","os":"ALL","width":"1024","height":"800","orientation":"ANY"},{"name":"Tablet","os":"ALL","width":"768","height":"1024","orientation":"ANY"},{"name":"Mobile","os":"ALL","width":"340","height":"680","orientation":"PORTRAIT"}],"conversations":{"convids":[],"convdescs":[],"rulesbeans":[],"nlpsbeans":[],"convinterfaces":{},"convscripts":{}},"screens":["AddPromotion","PromotionsList","Recommendation","ViewPromotion"],"loMap":{"AddPromotion":{"Web":{"PORTRAIT":"All","LANDSCAPE":"All"},"Tablet":{"PORTRAIT":"All","LANDSCAPE":"All"},"Mobile":{"PORTRAIT":"All","LANDSCAPE":"All"}},"PromotionsList":{"Web":{"PORTRAIT":"All","LANDSCAPE":"All"},"Tablet":{"PORTRAIT":"All","LANDSCAPE":"All"},"Mobile":{"PORTRAIT":"All","LANDSCAPE":"All"}},"Recommendation":{"Web":{"PORTRAIT":"All","LANDSCAPE":"All"},"Tablet":{"PORTRAIT":"All","LANDSCAPE":"All"},"Mobile":{"PORTRAIT":"All","LANDSCAPE":"All"}},"ViewPromotion":{"Web":{"PORTRAIT":"All","LANDSCAPE":"All"},"Tablet":{"PORTRAIT":"All","LANDSCAPE":"All"},"Mobile":{"PORTRAIT":"All","LANDSCAPE":"All"}}},"userPrefs":{},"props":{"offlineSupport":"N","appId":"promtn","firstPage":"ViewPromotion","serverToken":"TchNW1ihumFOPXgcmtLYog==","defaultAuthorization":"N","otpReqd":"N","trackLocation":"N","serverUrl":"http://localhost:8080/AppzillonCorpServer/Appzillon","auditLogReqd":"N","noOfLogLines":100,"logLevel":"D","authenticationType":"#DeviceId","sendLog":"N","useProcessJson":"N","enableMockServer":true,"enableAnimation":"Y","sslPinning":"N","trustAllCertificates":"N","payloadEncryption":"N","dataIntegrity":"N","enableServer":"Y"},"internalInterfaces":{},"appzillonVersion":"3.5.21"}