{"name":"bilpay__AccountSelection","type":"CUSTOM","offline":"N","session":"Y","correctReq":"N","noOfReqNodes":1,"correctRes":"N","noOfResNodes":2,"noOFaultNodes":1,"nodes":["bilpay__AccountSelection_Req","bilpay__AccountSelection_Res","Accounts","bilpay__AccountSelection_Flt"],"noOfNodeElms":[0,0,6,0],"nExtName":["bilpay__AccountSelection_Req","bilpay__AccountSelection_Res","Accounts","bilpay__AccountSelection_Flt"],"nMultiRec":["N","N","Y","N"],"nParent":["","","bilpay__AccountSelection_Res",""],"nParents":["","","bilpay__AccountSelection_Res",""],"nChilds":["","Accounts","",""],"nRelType":["1:1","1:1","1:N","1:1"],"nMrParent":["bilpay__AccountSelection_Req","bilpay__AccountSelection_Res","Accounts","bilpay__AccountSelection_Flt"],"elms":["title","cardname","accountno","accountnomasked","balance","ccy"],"eExtName":["title","cardname","accountno","accountnomasked","balance","ccy"],"eDataType":["STRING","STRING","STRING","STRING","NUMBER","STRING"],"eMinVal":["","","","","",""],"eMaxVal":["","","","","",""],"eMaxDec":["","","","","",""],"eLenType":["F","F","F","F","F","F"],"eMinLen":["","","","","",""],"eMaxLen":["","","","","",""],"eArr":["N","N","N","N","N","N"],"ePattern":["","","","","",""],"eMand":["N","N","N","N","N","N"],"eRelNode":["","","","","",""],"eRelElm":["","","","","",""]}