{"lits":{"en":{"LIT_CANCEL":"Cancel","LIT_OK":"Ok","LIT_GO":"Go"}},"msgs":{},"lovs":{},"deviceGroups":[{"name":"All","os":"ALL","width":"1000","height":"2000","orientation":"ANY"}],"conversations":{"convids":[],"convdescs":[],"rulesbeans":[],"nlpsbeans":[],"convinterfaces":{},"convscripts":{}},"screens":["AccountGroupDetails","AccountGroupLauncher","AccountGroupSummary","AuthMatrixDetails","AuthMatrixLauncher","AuthMatrixSummary"],"loMap":{"AccountGroupDetails":{"All":{"PORTRAIT":"All","LANDSCAPE":"All"}},"AccountGroupLauncher":{"All":{"PORTRAIT":"All","LANDSCAPE":"All"}},"AccountGroupSummary":{"All":{"PORTRAIT":"All","LANDSCAPE":"All"}},"AuthMatrixDetails":{"All":{"PORTRAIT":"All","LANDSCAPE":"All"}},"AuthMatrixLauncher":{"All":{"PORTRAIT":"All","LANDSCAPE":"All"}},"AuthMatrixSummary":{"All":{"PORTRAIT":"All","LANDSCAPE":"All"}}},"userPrefs":{},"props":{"offlineSupport":"N","appId":"authma","firstPage":"AuthMatrixDetails","serverToken":"U7A9mc3KXbsc+kzRP2vMYQ==","defaultAuthorization":"N","otpReqd":"N","trackLocation":"N","serverUrl":"http://localhost:8080/AppzillonCorpServer/Appzillon","auditLogReqd":"N","noOfLogLines":100,"logLevel":"D","authenticationType":"#DeviceId","sendLog":"N","useProcessJson":"N","enableMockServer":true,"enableAnimation":"Y","sslPinning":"N","trustAllCertificates":"N","payloadEncryption":"N","dataIntegrity":"Y","enableServer":"Y"},"internalInterfaces":{},"appzillonVersion":"3.5.21"}