{
    "CommitmentList": [
        {
            "commitmentId":"CM903479093",
            "totalCommitmentvalue": "200000",
            "counterPartyname": "Jack Kricher",
            "currency": "USD"
        },
        {
            "commitmentId":"CM903478094",
            "totalCommitmentvalue": "100000",
            "counterPartyname": "Joan Kim",
            "currency": "USD"
        },
        {
            "commitmentId":"CM903476096",
            "totalCommitmentvalue": "300000",
            "counterPartyname": "John Thomas",
            "currency": "USD"
        },
        {
            "commitmentId":"CM903476099",
            "totalCommitmentvalue": "500000",
            "counterPartyname": "Scott Mack",
            "currency": "USD"
        },
        {
            "commitmentId":"CM903475093",
            "totalCommitmentvalue": "900000",
            "counterPartyname": "Jane Jones",
            "currency": "USD"
        }
    ],
    "CommitmentDetails":{
        
         "commitmentId":"CL903475093",
         "counterPartyname":"Jack Kricher",
         "currency":"USD",
         "typeofCommitment":"Revolving",
         "totalCommitmentvalue":"200000",
         "startdate":"2018-02-15",
         "maturitydate":"2018-05-18",
         "availableAmount":"100000",
         "availedAmount":"100000",
         "previousPaidCommissions":"100"
    },
    
    "LoansAssociated":[
         {
            "loanName": "Loan",
            "accountName": "Capital Loan",
            "accountNo": "150100159521",
            "amount":"87698700",
            "currency":"USD"
           
        },
         {
            "loanName": "Loan",
            "accountName": "Capital Loan",
            "accountNo": "150100159521",
            "amount":"87698700",
            "currency":"USD"
           
        },
         {
             "loanName": "Loan",
            "accountName": "Capital Loan",
            "accountNo": "150100159521",
            "amount":"87698700",
            "currency":"USD"
           
        }
    ],
    "Status":true
}
